kateryna/__init__.py
kateryna/detector.py
kateryna/state.py
kateryna/adapters/__init__.py
kateryna/adapters/anthropic.py
kateryna/adapters/base.py
kateryna/adapters/ollama.py
kateryna/adapters/openai.py
kateryna/languages/__init__.py
kateryna/languages/de.py
kateryna/languages/en.py
kateryna-1.1.0.dist-info/METADATA
kateryna-1.1.0.dist-info/WHEEL
kateryna-1.1.0.dist-info/entry_points.txt
kateryna-1.1.0.dist-info/licenses/LICENSE
kateryna-1.1.0.dist-info/RECORD
