Metadata-Version: 2.4
Name: kateryna
Version: 1.1.0
Summary: Epistemic uncertainty layer for LLMs. Stop hallucinations. Let AI say 'I don't know.'
Project-URL: Homepage, https://github.com/Zaneham/kateryna
Project-URL: Documentation, https://github.com/Zaneham/kateryna#readme
Project-URL: Repository, https://github.com/Zaneham/kateryna
Project-URL: Issues, https://github.com/Zaneham/kateryna/issues
Author: Zane Hambly
License: MIT
License-File: LICENSE
Keywords: ai,anthropic,claude,epistemic,gpt,hallucination,llama,llm,mistral,ollama,openai,rag,setun,ternary,uncertainty
Classifier: Development Status :: 5 - Production/Stable
Classifier: Intended Audience :: Developers
Classifier: Intended Audience :: Science/Research
Classifier: License :: OSI Approved :: MIT License
Classifier: Programming Language :: Python :: 3
Classifier: Programming Language :: Python :: 3.9
Classifier: Programming Language :: Python :: 3.10
Classifier: Programming Language :: Python :: 3.11
Classifier: Programming Language :: Python :: 3.12
Classifier: Topic :: Scientific/Engineering :: Artificial Intelligence
Classifier: Topic :: Software Development :: Libraries :: Python Modules
Requires-Python: >=3.9
Provides-Extra: all
Requires-Dist: anthropic>=0.18.0; extra == 'all'
Requires-Dist: httpx>=0.24.0; extra == 'all'
Requires-Dist: openai>=1.0.0; extra == 'all'
Provides-Extra: anthropic
Requires-Dist: anthropic>=0.18.0; extra == 'anthropic'
Provides-Extra: dev
Requires-Dist: black>=23.0.0; extra == 'dev'
Requires-Dist: pytest-asyncio>=0.21.0; extra == 'dev'
Requires-Dist: pytest>=7.0.0; extra == 'dev'
Requires-Dist: ruff>=0.1.0; extra == 'dev'
Provides-Extra: ollama
Requires-Dist: httpx>=0.24.0; extra == 'ollama'
Provides-Extra: openai
Requires-Dist: openai>=1.0.0; extra == 'openai'
